autora/experimentalist/sampler/model_disagreement/__init__.py
autora_experimentalist_sampler_model_disagreement-1.0.4.dist-info/METADATA
autora_experimentalist_sampler_model_disagreement-1.0.4.dist-info/WHEEL
autora_experimentalist_sampler_model_disagreement-1.0.4.dist-info/top_level.txt
autora_experimentalist_sampler_model_disagreement-1.0.4.dist-info/RECORD
